[
    {
        "o": 25748,
        "r": "nkjv:Zechariah:7:0",
        "t": "Zechariah 7",
        "h": 1
    },
    {
        "o": 25749,
        "r": "nkjv:Zechariah:7:0",
        "t": "Obedience Better than Fasting",
        "h": 2
    },
    {
        "o": 25750,
        "r": "nkjv:Zechariah:7:1",
        "t": "Now*p in the fourth year of King Darius it came to pass that*i the word of the Lord*s came to Zechariah, on the fourth day*i of the ninth month, Chislev,"
    },
    {
        "o": 25751,
        "r": "nkjv:Zechariah:7:2",
        "t": "when the*i people*i sent Sherezer, with Regem-Melech and his men, to*i the house of God, to pray before the Lord,*s"
    },
    {
        "o": 25752,
        "r": "nkjv:Zechariah:7:3",
        "t": "and*i to ask the priests who were*i in the house of the Lord*s of hosts, and the prophets, saying, “Should I weep in the fifth month and fast as I have done for so many years?”"
    },
    {
        "o": 25753,
        "r": "nkjv:Zechariah:7:4",
        "t": "Then*p the word of the Lord*s of hosts came to me, saying,"
    },
    {
        "o": 25754,
        "r": "nkjv:Zechariah:7:5",
        "t": "“Say to all the people of the land, and to the priests: ‘When you fasted and mourned in the fifth and seventh months*i during those seventy years, did you really fast for Me—for Me?"
    },
    {
        "o": 25755,
        "r": "nkjv:Zechariah:7:6",
        "t": "When you eat and when you drink, do you not eat and drink for*i yourselves?*i"
    },
    {
        "o": 25756,
        "r": "nkjv:Zechariah:7:7",
        "t": "Should*i you*i not have*i obeyed*i the words which the Lord*s proclaimed through the former prophets when Jerusalem and the cities around it were inhabited and prosperous, and the South and the Lowland were inhabited?’”"
    },
    {
        "o": 25757,
        "r": "nkjv:Zechariah:7:7",
        "t": "Disobedience Resulted in Captivity",
        "h": 2
    },
    {
        "o": 25758,
        "r": "nkjv:Zechariah:7:8",
        "t": "Then*p the word of the Lord*s came to Zechariah, saying,"
    },
    {
        "o": 25759,
        "r": "nkjv:Zechariah:7:9",
        "t": "“Thus says the Lord*s of hosts: ‘Execute*pn true justice, Show*ld mercy and compassion Everyone*ld to his brother."
    },
    {
        "o": 25760,
        "r": "nkjv:Zechariah:7:10",
        "t": "Do*ld not oppress the widow or the fatherless, The*ld alien or the poor. Let*ld none of you plan evil in his heart Against*ld his brother.’"
    },
    {
        "o": 25761,
        "r": "nkjv:Zechariah:7:11",
        "t": "“But*p they refused to heed, shrugged their shoulders, and stopped their ears so that they could not hear."
    },
    {
        "o": 25762,
        "r": "nkjv:Zechariah:7:12",
        "t": "Yes, they made their hearts like flint, refusing to hear the law and the words which the Lord*s of hosts had sent by His Spirit through the former prophets. Thus great wrath came from the Lord*s of hosts."
    },
    {
        "o": 25763,
        "r": "nkjv:Zechariah:7:13",
        "t": "Therefore it happened, that*i just as He proclaimed and they would not hear, so they called out and I would not listen,” says the Lord*s of hosts."
    },
    {
        "o": 25764,
        "r": "nkjv:Zechariah:7:14",
        "t": "“But I scattered them with a whirlwind among all the nations which they had not known. Thus the land became desolate after them, so that no one passed through or returned; for they made the pleasant land desolate.”"
    }
]
