[
    {
        "o": 16035,
        "r": "nkjv:Psalm:37:0",
        "t": "Psalm 37",
        "h": 1
    },
    {
        "o": 16036,
        "r": "nkjv:Psalm:37:0",
        "t": "The Heritage of the Righteous and the Calamity of the Wicked",
        "h": 2
    },
    {
        "o": 16037,
        "r": "nkjv:Psalm:37:0",
        "t": "A Psalm of David.",
        "h": 4
    },
    {
        "o": 16038,
        "r": "nkjv:Psalm:37:1",
        "t": "Do*pn not fret because of evildoers, Nor*ld be envious of the workers of iniquity."
    },
    {
        "o": 16039,
        "r": "nkjv:Psalm:37:2",
        "t": "For*ld they shall soon be cut down like the grass, And*ld wither as the green herb."
    },
    {
        "o": 16040,
        "r": "nkjv:Psalm:37:3",
        "t": "Trust*ln in the Lord,*s and do good; Dwell*ld in the land, and feed on His faithfulness."
    },
    {
        "o": 16041,
        "r": "nkjv:Psalm:37:4",
        "t": "Delight*ld yourself also in the Lord,*s And*ld He shall give you the desires of your heart."
    },
    {
        "o": 16042,
        "r": "nkjv:Psalm:37:5",
        "t": "Commit*ln your way to the Lord,*s Trust*ld also in Him, And*ld He shall bring it*i to pass."
    },
    {
        "o": 16043,
        "r": "nkjv:Psalm:37:6",
        "t": "He*ld shall bring forth your righteousness as the light, And*ld your justice as the noonday."
    },
    {
        "o": 16044,
        "r": "nkjv:Psalm:37:7",
        "t": "Rest*ln in the Lord,*s and wait patiently for Him; Do*ld not fret because of him who prospers in his way, Because*ld of the man who brings wicked schemes to pass."
    },
    {
        "o": 16045,
        "r": "nkjv:Psalm:37:8",
        "t": "Cease*ld from anger, and forsake wrath; Do*ld not fret— it*i only causes*i harm."
    },
    {
        "o": 16046,
        "r": "nkjv:Psalm:37:9",
        "t": "For*ln evildoers shall be cut off; But*ld those who wait on the Lord,*s They*ld shall inherit the earth."
    },
    {
        "o": 16047,
        "r": "nkjv:Psalm:37:10",
        "t": "For*ld yet a little while and the wicked shall*i be*i no more;*i Indeed,*ld you will look carefully for his place, But*ld it shall*i be*i no more.*i"
    },
    {
        "o": 16048,
        "r": "nkjv:Psalm:37:11",
        "t": "But*ld the meek shall inherit the earth, And*ld shall delight themselves in the abundance of peace."
    },
    {
        "o": 16049,
        "r": "nkjv:Psalm:37:12",
        "t": "The*ln wicked plots against the just, And*ld gnashes at him with his teeth."
    },
    {
        "o": 16050,
        "r": "nkjv:Psalm:37:13",
        "t": "The*ld Lord laughs at him, For*ld He sees that his day is coming."
    },
    {
        "o": 16051,
        "r": "nkjv:Psalm:37:14",
        "t": "The*ld wicked have drawn the sword And*ld have bent their bow, To*ld cast down the poor and needy, To*ld slay those who are of upright conduct."
    },
    {
        "o": 16052,
        "r": "nkjv:Psalm:37:15",
        "t": "Their*ld sword shall enter their own heart, And*ld their bows shall be broken."
    },
    {
        "o": 16053,
        "r": "nkjv:Psalm:37:16",
        "t": "A*ln little that a righteous man has Is*ild better than the riches of many wicked."
    },
    {
        "o": 16054,
        "r": "nkjv:Psalm:37:17",
        "t": "For*ld the arms of the wicked shall be broken, But*ld the Lord*s upholds the righteous."
    },
    {
        "o": 16055,
        "r": "nkjv:Psalm:37:18",
        "t": "The*ln Lord*s knows the days of the upright, And*ld their inheritance shall be forever."
    },
    {
        "o": 16056,
        "r": "nkjv:Psalm:37:19",
        "t": "They*ld shall not be ashamed in the evil time, And*ld in the days of famine they shall be satisfied."
    },
    {
        "o": 16057,
        "r": "nkjv:Psalm:37:20",
        "t": "But*ld the wicked shall perish; And*ld the enemies of the Lord,*s Like*ld the splendor of the meadows, shall vanish. Into*ld smoke they shall vanish away."
    },
    {
        "o": 16058,
        "r": "nkjv:Psalm:37:21",
        "t": "The*ln wicked borrows and does not repay, But*ld the righteous shows mercy and gives."
    },
    {
        "o": 16059,
        "r": "nkjv:Psalm:37:22",
        "t": "For*ld those*i blessed by Him shall inherit the earth, But*ld those*i cursed by Him shall be cut off."
    },
    {
        "o": 16060,
        "r": "nkjv:Psalm:37:23",
        "t": "The*ln steps of a good*i man are ordered by the Lord,*s And*ld He delights in his way."
    },
    {
        "o": 16061,
        "r": "nkjv:Psalm:37:24",
        "t": "Though*ld he fall, he shall not be utterly cast down; For*ld the Lord*s upholds him*i with*i His hand."
    },
    {
        "o": 16062,
        "r": "nkjv:Psalm:37:25",
        "t": "I*ln have been young, and now*i am old; Yet*ld I have not seen the righteous forsaken, Nor*ld his descendants begging bread."
    },
    {
        "o": 16063,
        "r": "nkjv:Psalm:37:26",
        "t": "He*ild is*i ever merciful, and lends; And*ld his descendants are*i blessed."
    },
    {
        "o": 16064,
        "r": "nkjv:Psalm:37:27",
        "t": "Depart*ln from evil, and do good; And*ld dwell forevermore."
    },
    {
        "o": 16065,
        "r": "nkjv:Psalm:37:28",
        "t": "For*ld the Lord*s loves justice, And*ld does not forsake His saints; They*ld are preserved forever, But*ld the descendants of the wicked shall be cut off."
    },
    {
        "o": 16066,
        "r": "nkjv:Psalm:37:29",
        "t": "The*ld righteous shall inherit the land, And*ld dwell in it forever."
    },
    {
        "o": 16067,
        "r": "nkjv:Psalm:37:30",
        "t": "The*ln mouth of the righteous speaks wisdom, And*ld his tongue talks of justice."
    },
    {
        "o": 16068,
        "r": "nkjv:Psalm:37:31",
        "t": "The*ld law of his God is*i in his heart; None*ld of his steps shall slide."
    },
    {
        "o": 16069,
        "r": "nkjv:Psalm:37:32",
        "t": "The*ln wicked watches the righteous, And*ld seeks to slay him."
    },
    {
        "o": 16070,
        "r": "nkjv:Psalm:37:33",
        "t": "The*ld Lord*s will not leave him in his hand, Nor*ld condemn him when he is judged."
    },
    {
        "o": 16071,
        "r": "nkjv:Psalm:37:34",
        "t": "Wait*ln on the Lord,*s And*ld keep His way, And*ld He shall exalt you to inherit the land; When*ld the wicked are cut off, you shall see it.*i"
    },
    {
        "o": 16072,
        "r": "nkjv:Psalm:37:35",
        "t": "I*ld have seen the wicked in great power, And*ld spreading himself like a native green tree."
    },
    {
        "o": 16073,
        "r": "nkjv:Psalm:37:36",
        "t": "Yet*ld he passed away, and behold, he was*i no more;*i Indeed*ld I sought him, but he could not be found."
    },
    {
        "o": 16074,
        "r": "nkjv:Psalm:37:37",
        "t": "Mark*ln the blameless man,*i and observe the upright; For*ld the future of that*i man is*i peace."
    },
    {
        "o": 16075,
        "r": "nkjv:Psalm:37:38",
        "t": "But*ld the transgressors shall be destroyed together; The*ld future of the wicked shall be cut off."
    },
    {
        "o": 16076,
        "r": "nkjv:Psalm:37:39",
        "t": "But*ln the salvation of the righteous is*i from the Lord;*s He*ild is*i their strength in the time of trouble."
    },
    {
        "o": 16077,
        "r": "nkjv:Psalm:37:40",
        "t": "And*ld the Lord*s shall help them and deliver them; He*ld shall deliver them from the wicked, And*ld save them, Because*ld they trust in Him."
    }
]
