[
    {
        "o": 5510,
        "r": "esv:Deuteronomy:5:2",
        "w": 0,
        "l": {},
        "c": "Deuteronomy 4:23*5477; Exodus 19:5*2213",
        "a": "a"
    },
    {
        "o": 5511,
        "r": "esv:Deuteronomy:5:3",
        "w": 0,
        "l": {},
        "c": "Hebrews 8:9*33702",
        "a": "b"
    },
    {
        "o": 5512,
        "r": "esv:Deuteronomy:5:4",
        "w": 4,
        "l": {},
        "c": "Deuteronomy 34:10*6389; Exodus 33:11*2708; Numbers 14:14*4486; Judges 6:22*7302",
        "a": "c"
    },
    {
        "o": 5513,
        "r": "esv:Deuteronomy:5:5",
        "w": 0,
        "l": {},
        "c": "Exodus 20:21*2257; Galatians 3:19*32571",
        "a": "d"
    },
    {
        "o": 5513,
        "r": "esv:Deuteronomy:5:5",
        "w": 20,
        "l": {},
        "c": "Exodus 19:16*2224; Exodus 20:18*2253; Exodus 24:2*2374",
        "a": "e"
    },
    {
        "o": 5514,
        "r": "esv:Deuteronomy:5:6",
        "w": 0,
        "l": {},
        "c": "Deuteronomy 5:6–21*5514; Exodus 20:2–17*2237",
        "a": "f"
    },
    {
        "o": 5515,
        "r": "esv:Deuteronomy:5:7",
        "w": 6,
        "l": {},
        "t": "Or besides*i",
        "a": "g"
    },
    {
        "o": 5518,
        "r": "esv:Deuteronomy:5:10",
        "w": 4,
        "l": {},
        "c": "Exodus 20:6*2241; Jeremiah 32:18*21973",
        "a": "h"
    },
    {
        "o": 5518,
        "r": "esv:Deuteronomy:5:10",
        "w": 5,
        "l": {},
        "t": "Or to*i the*i thousandth*i generation*i",
        "a": "i"
    },
    {
        "o": 5522,
        "r": "esv:Deuteronomy:5:14",
        "w": 0,
        "l": {},
        "c": "Exodus 16:29–30*2151; Hebrews 4:4*33609",
        "a": "j"
    },
    {
        "o": 5522,
        "r": "esv:Deuteronomy:5:14",
        "w": 53,
        "l": {},
        "c": "Exodus 23:12*2348",
        "a": "k"
    },
    {
        "o": 5523,
        "r": "esv:Deuteronomy:5:15",
        "w": 0,
        "l": {},
        "c": "Deuteronomy 15:15*5812; Deuteronomy 16:12*5836; Deuteronomy 24:18*6056; Deuteronomy 24:22*6060",
        "a": "l"
    },
    {
        "o": 5523,
        "r": "esv:Deuteronomy:5:15",
        "w": 7,
        "l": {},
        "t": "Or servant*i",
        "a": "m"
    },
    {
        "o": 5523,
        "r": "esv:Deuteronomy:5:15",
        "w": 22,
        "l": {},
        "c": "Deuteronomy 4:34*5489",
        "a": "n"
    },
    {
        "o": 5524,
        "r": "esv:Deuteronomy:5:16",
        "w": 12,
        "l": {},
        "c": "Deuteronomy 4:40*5496",
        "a": "o"
    },
    {
        "o": 5525,
        "r": "esv:Deuteronomy:5:17",
        "w": 0,
        "l": {},
        "c": "Matthew 5:21*25908; Matthew 5:27*25915; Luke 18:20*28746; James 2:11*33927",
        "a": "p"
    },
    {
        "o": 5525,
        "r": "esv:Deuteronomy:5:17",
        "w": 3,
        "l": {},
        "t": "The Hebrew word also covers causing human death through carelessness or negligence",
        "a": "q"
    },
    {
        "o": 5526,
        "r": "esv:Deuteronomy:5:18",
        "w": 0,
        "l": {},
        "c": "Deuteronomy 5:17*5525",
        "a": "r"
    },
    {
        "o": 5530,
        "r": "esv:Deuteronomy:5:22",
        "w": 8,
        "l": {},
        "c": "Deuteronomy 4:11*5464",
        "a": "s"
    },
    {
        "o": 5530,
        "r": "esv:Deuteronomy:5:22",
        "w": 34,
        "l": {},
        "c": "Deuteronomy 9:10–11*5630; Exodus 24:12*2384",
        "a": "t"
    },
    {
        "o": 5531,
        "r": "esv:Deuteronomy:5:23",
        "w": 0,
        "l": {},
        "c": "Deuteronomy 4:12*5465",
        "a": "u"
    },
    {
        "o": 5532,
        "r": "esv:Deuteronomy:5:24",
        "w": 13,
        "l": {},
        "c": "Deuteronomy 3:24*5446",
        "a": "v"
    },
    {
        "o": 5532,
        "r": "esv:Deuteronomy:5:24",
        "w": 15,
        "l": {},
        "c": "Exodus 19:19*2227",
        "a": "w"
    },
    {
        "o": 5532,
        "r": "esv:Deuteronomy:5:24",
        "w": 38,
        "l": {},
        "c": "Deuteronomy 4:33*5488",
        "a": "x"
    },
    {
        "o": 5533,
        "r": "esv:Deuteronomy:5:25",
        "w": 12,
        "l": {},
        "c": "Deuteronomy 18:16*5891",
        "a": "y"
    },
    {
        "o": 5534,
        "r": "esv:Deuteronomy:5:26",
        "w": 0,
        "l": {},
        "c": "Deuteronomy 5:24*5532",
        "a": "z"
    },
    {
        "o": 5535,
        "r": "esv:Deuteronomy:5:27",
        "w": 12,
        "l": {},
        "c": "Exodus 20:19*2254",
        "a": "a"
    },
    {
        "o": 5536,
        "r": "esv:Deuteronomy:5:28",
        "w": 30,
        "l": {},
        "c": "Deuteronomy 18:17*5892",
        "a": "b"
    },
    {
        "o": 5537,
        "r": "esv:Deuteronomy:5:29",
        "w": 0,
        "l": {},
        "c": "Deuteronomy 32:29*6322; Psalm 81:13*16862; Isaiah 48:18*20730; Matthew 23:37*26724; Luke 19:42*28818",
        "a": "c"
    },
    {
        "o": 5537,
        "r": "esv:Deuteronomy:5:29",
        "w": 18,
        "l": {},
        "c": "Deuteronomy 4:40*5496",
        "a": "d"
    },
    {
        "o": 5537,
        "r": "esv:Deuteronomy:5:29",
        "w": 29,
        "l": {},
        "t": "Or sons*i",
        "a": "e"
    },
    {
        "o": 5539,
        "r": "esv:Deuteronomy:5:31",
        "w": 6,
        "l": {},
        "c": "Galatians 3:19*32571",
        "a": "f"
    },
    {
        "o": 5540,
        "r": "esv:Deuteronomy:5:32",
        "w": 14,
        "l": {},
        "c": "Deuteronomy 17:20*5871; Deuteronomy 28:14*6149; Joshua 1:7*6400; Joshua 23:6*7069; 2 Kings 22:2*11152; Proverbs 4:27*18363",
        "a": "g"
    },
    {
        "o": 5541,
        "r": "esv:Deuteronomy:5:33",
        "w": 0,
        "l": {},
        "c": "Deuteronomy 10:12*5665; Deuteronomy 30:16*6253; Jeremiah 7:23*21300; Luke 1:6*27813",
        "a": "h"
    },
    {
        "o": 5541,
        "r": "esv:Deuteronomy:5:33",
        "w": 19,
        "l": {},
        "c": "Deuteronomy 4:40*5496",
        "a": "i"
    }
]
