[
    {
        "o": 26686,
        "r": "csb:Matthew:15:1",
        "w": 0,
        "l": {},
        "c": "Mk 7:1–23*27637",
        "a": "a"
    },
    {
        "o": 26686,
        "r": "csb:Matthew:15:1",
        "w": 11,
        "l": {},
        "c": "Mk 3:22*27461; Jn 1:19*29484",
        "a": "b"
    },
    {
        "o": 26687,
        "r": "csb:Matthew:15:2",
        "w": 3,
        "l": {},
        "c": "Mt 10:1*26434; 26:56*27227; Mk 3:7*27444; 16:20*28132; Lk 6:13*28434; Jn 12:16*30073",
        "a": "c"
    },
    {
        "o": 26687,
        "r": "csb:Matthew:15:2",
        "w": 18,
        "l": {},
        "t": "15:2*r Lit eat bread = eat a meal",
        "a": "d"
    },
    {
        "o": 26687,
        "r": "csb:Matthew:15:2",
        "w": 18,
        "l": {},
        "c": "Lk 11:38*28772; Gl 1:14*32918; Col 2:8*33414; Heb 11:2*34207",
        "a": "e"
    },
    {
        "o": 26689,
        "r": "csb:Matthew:15:4",
        "w": 2,
        "l": {},
        "t": "15:4*r Other mss read commanded, saying",
        "a": "f"
    },
    {
        "o": 26689,
        "r": "csb:Matthew:15:4",
        "w": 8,
        "l": {},
        "t": "15:4*r Ex 20:12; Dt 5:16",
        "a": "g"
    },
    {
        "o": 26689,
        "r": "csb:Matthew:15:4",
        "w": 8,
        "l": {},
        "c": "Ex 20:12*2273; Dt 5:16*5575; Eph 6:2*33223",
        "a": "h"
    },
    {
        "o": 26689,
        "r": "csb:Matthew:15:4",
        "w": 21,
        "l": {},
        "t": "15:4*r Ex 21:17; Lv 20:9",
        "a": "i"
    },
    {
        "o": 26689,
        "r": "csb:Matthew:15:4",
        "w": 21,
        "l": {},
        "c": "Ex 21:17*2309; Lv 20:9*3678",
        "a": "j"
    },
    {
        "o": 26691,
        "r": "csb:Matthew:15:6",
        "w": 7,
        "l": {},
        "t": "15:6*r Other mss read then he does not have to honor his father or mother",
        "a": "k"
    },
    {
        "o": 26691,
        "r": "csb:Matthew:15:6",
        "w": 17,
        "l": {},
        "t": "15:6*r Other mss read commandment",
        "a": "l"
    },
    {
        "o": 26693,
        "r": "csb:Matthew:15:8",
        "w": 1,
        "l": {},
        "t": "15:8*r Other mss add draw near to me with their mouths, and",
        "a": "m"
    },
    {
        "o": 26694,
        "r": "csb:Matthew:15:9",
        "w": 9,
        "l": {},
        "t": "15:8–9*r Is 29:13 LXX",
        "a": "n"
    },
    {
        "o": 26694,
        "r": "csb:Matthew:15:9",
        "w": 9,
        "l": {},
        "c": "Is 29:13*20395; Ezk 33:31*23975; Col 2:22*33428; Ti 1:14*33896",
        "a": "o"
    },
    {
        "o": 26697,
        "r": "csb:Matthew:15:11",
        "w": 8,
        "l": {},
        "c": "Mt 15:18*26704; Mk 7:15*27651; Ac 21:28*31337; Heb 9:13*34145",
        "a": "p"
    },
    {
        "o": 26697,
        "r": "csb:Matthew:15:11",
        "w": 21,
        "l": {},
        "c": "Ac 10:14–15*30862; 1Tm 4:3*33710",
        "a": "q"
    },
    {
        "o": 26699,
        "r": "csb:Matthew:15:13",
        "w": 12,
        "l": {},
        "c": "Is 60:21*21107; 61:3*21113; Jn 15:2*30196; 1Co 3:9*32174",
        "a": "r"
    },
    {
        "o": 26700,
        "r": "csb:Matthew:15:14",
        "w": 6,
        "l": {},
        "t": "15:14*r Other mss add for the blind",
        "a": "s"
    },
    {
        "o": 26700,
        "r": "csb:Matthew:15:14",
        "w": 19,
        "l": {},
        "c": "Mal 2:8*26059; Mt 23:16,24*27028; Lk 6:39*28465",
        "a": "t"
    },
    {
        "o": 26701,
        "r": "csb:Matthew:15:15",
        "w": 7,
        "l": {},
        "c": "Mt 13:36*26616; Mk 7:17*27652",
        "a": "u"
    },
    {
        "o": 26702,
        "r": "csb:Matthew:15:16",
        "w": 5,
        "l": {},
        "t": "15:16*r Other mss read Jesus",
        "a": "v"
    },
    {
        "o": 26703,
        "r": "csb:Matthew:15:17",
        "w": 2,
        "l": {},
        "t": "15:17*r Other mss add yet",
        "a": "w"
    },
    {
        "o": 26703,
        "r": "csb:Matthew:15:17",
        "w": 15,
        "l": {},
        "t": "15:17*r Lit and goes out into the toilet",
        "a": "x"
    },
    {
        "o": 26704,
        "r": "csb:Matthew:15:18",
        "w": 15,
        "l": {},
        "c": "Mt 12:34*26553; Jms 3:6*34374",
        "a": "y"
    },
    {
        "o": 26705,
        "r": "csb:Matthew:15:19",
        "w": 13,
        "l": {},
        "c": "Eph 4:31*33181; Col 3:8*33439; 1Tm 6:4*33761",
        "a": "z"
    },
    {
        "o": 26705,
        "r": "csb:Matthew:15:19",
        "w": 14,
        "l": {},
        "c": "Ex 20:13–16*2274; Gl 5:19–21*33042; Jms 2:4*34343",
        "a": "a"
    },
    {
        "o": 26706,
        "r": "csb:Matthew:15:20",
        "w": 17,
        "l": {},
        "c": "Mt 11:18*26500; Mk 7:2,5*27638; 1Co 6:9–10*32241",
        "a": "b"
    },
    {
        "o": 26708,
        "r": "csb:Matthew:15:21",
        "w": 3,
        "l": {},
        "c": "Mk 7:24–30*27660",
        "a": "c"
    },
    {
        "o": 26708,
        "r": "csb:Matthew:15:21",
        "w": 12,
        "l": {},
        "c": "Mt 11:21*26503; Mk 7:24*27660",
        "a": "d"
    },
    {
        "o": 26709,
        "r": "csb:Matthew:15:22",
        "w": 12,
        "l": {},
        "t": "15:22*r Other mss read and cried out to him",
        "a": "e"
    },
    {
        "o": 26709,
        "r": "csb:Matthew:15:22",
        "w": 28,
        "l": {},
        "c": "Gn 10:15,19*277; Jdg 1:30–33*7241; Mt 4:24*26209; 9:27*26418",
        "a": "f"
    },
    {
        "o": 26710,
        "r": "csb:Matthew:15:23",
        "w": 9,
        "l": {},
        "c": "Mt 10:1*26434; 26:56*27227; Mk 3:7*27444; 16:20*28132; Lk 6:13*28434; Jn 12:16*30073",
        "a": "g"
    },
    {
        "o": 26711,
        "r": "csb:Matthew:15:24",
        "w": 14,
        "l": {},
        "c": "Mt 10:6,23*26439; Jn 4:22*29610; Rm 15:8*32047",
        "a": "h"
    },
    {
        "o": 26713,
        "r": "csb:Matthew:15:26",
        "w": 15,
        "l": {},
        "c": "Ex 22:31*2367; 2Kg 9:10*10803; Mt 8:2*26348; Php 3:2*33322",
        "a": "i"
    },
    {
        "o": 26715,
        "r": "csb:Matthew:15:28",
        "w": 22,
        "l": {},
        "t": "15:28*r Lit hour",
        "a": "j"
    },
    {
        "o": 26715,
        "r": "csb:Matthew:15:28",
        "w": 26,
        "l": {},
        "c": "Mt 9:22*26412; 17:18*26782; Jn 4:52–53*29644",
        "a": "k"
    },
    {
        "o": 26717,
        "r": "csb:Matthew:15:29",
        "w": 3,
        "l": {},
        "c": "Mk 7:31–37*27668",
        "a": "l"
    },
    {
        "o": 26717,
        "r": "csb:Matthew:15:29",
        "w": 10,
        "l": {},
        "c": "Mt 9:8*26396; 18:8*26802; Mk 9:43*27769",
        "a": "m"
    },
    {
        "o": 26719,
        "r": "csb:Matthew:15:31",
        "w": 22,
        "l": {},
        "c": "Is 29:23*20405; Lk 1:68*28208; Ac 13:17*30983",
        "a": "n"
    },
    {
        "o": 26721,
        "r": "csb:Matthew:15:32",
        "w": 5,
        "l": {},
        "c": "Mt 14:14–21*26659; Mk 8:1–10*27677",
        "a": "o"
    },
    {
        "o": 26722,
        "r": "csb:Matthew:15:33",
        "w": 14,
        "l": {},
        "c": "Mk 8:4*27680; 2Co 11:26*32853; Heb 11:38*34243",
        "a": "p"
    },
    {
        "o": 26725,
        "r": "csb:Matthew:15:36",
        "w": 25,
        "l": {},
        "c": "Mt 26:27*27194; Lk 22:17*29279; Jn 6:11,23*29710; Ac 27:35*31557; Rm 14:6*32018; 1Co 10:30*32377",
        "a": "q"
    },
    {
        "o": 26728,
        "r": "csb:Matthew:15:39",
        "w": 15,
        "l": {},
        "t": "15:39*r Other mss read Magdala",
        "a": "r"
    },
    {
        "o": 26728,
        "r": "csb:Matthew:15:39",
        "w": 15,
        "l": {},
        "c": "Mk 3:9*27446; 8:10*27687",
        "a": "s"
    }
]
