[
    {
        "o": 8834,
        "r": "nkjv:1 Samuel:31:1",
        "w": 0,
        "l": {},
        "c": "1 Sam 23:22*8639",
        "a": "a"
    },
    {
        "o": 8834,
        "r": "nkjv:1 Samuel:31:1",
        "w": 20,
        "l": {},
        "c": "1 Chr 10:1–12*11801",
        "a": "b"
    },
    {
        "o": 8835,
        "r": "nkjv:1 Samuel:31:2",
        "w": 13,
        "l": {},
        "c": "1 Sam 28:4*8764",
        "a": "c"
    },
    {
        "o": 8836,
        "r": "nkjv:1 Samuel:31:3",
        "w": 0,
        "l": {},
        "c": "1 Sam 14:49*8340; 1 Chr 8:33*11740",
        "a": "d"
    },
    {
        "o": 8837,
        "r": "nkjv:1 Samuel:31:4",
        "w": 0,
        "l": {},
        "c": "2 Sam 1:6*8854",
        "a": "e"
    },
    {
        "o": 8837,
        "r": "nkjv:1 Samuel:31:4",
        "w": 15,
        "l": {},
        "c": "Judg 9:54*7508; 1 Chr 10:4*11804",
        "a": "f"
    },
    {
        "o": 8837,
        "r": "nkjv:1 Samuel:31:4",
        "w": 31,
        "l": {},
        "c": "Judg 14:3*7627; 1 Sam 14:6*8295; 17:26, 36*8435",
        "a": "g"
    },
    {
        "o": 8837,
        "r": "nkjv:1 Samuel:31:4",
        "w": 42,
        "l": {},
        "c": "2 Sam 1:14*8862",
        "a": "h"
    },
    {
        "o": 8842,
        "r": "nkjv:1 Samuel:31:9",
        "w": 20,
        "l": {},
        "c": "2 Sam 1:6, 10*8854",
        "a": "i"
    },
    {
        "o": 8843,
        "r": "nkjv:1 Samuel:31:10",
        "w": 0,
        "l": {},
        "c": "Judg 16:23, 24*7692; 2 Sam 1:20*8869",
        "a": "j"
    },
    {
        "o": 8843,
        "r": "nkjv:1 Samuel:31:10",
        "w": 9,
        "l": {},
        "c": "1 Sam 21:9*8582",
        "a": "k"
    },
    {
        "o": 8843,
        "r": "nkjv:1 Samuel:31:10",
        "w": 11,
        "l": {},
        "c": "Judg 2:13*7234; 1 Sam 7:3*8120",
        "a": "l"
    },
    {
        "o": 8843,
        "r": "nkjv:1 Samuel:31:10",
        "w": 19,
        "l": {},
        "c": "2 Sam 21:12*9487",
        "a": "m"
    },
    {
        "o": 8844,
        "r": "nkjv:1 Samuel:31:11",
        "w": 0,
        "l": {},
        "c": "Judg 1:27*7208",
        "a": "n"
    },
    {
        "o": 8845,
        "r": "nkjv:1 Samuel:31:12",
        "w": 0,
        "l": {},
        "c": "1 Sam 11:1–13*8220",
        "a": "o"
    },
    {
        "o": 8845,
        "r": "nkjv:1 Samuel:31:12",
        "w": 32,
        "l": {},
        "c": "1 Sam 11:1–11*8220; 2 Sam 2:4–7*8882",
        "a": "p"
    },
    {
        "o": 8846,
        "r": "nkjv:1 Samuel:31:13",
        "w": 5,
        "l": {},
        "c": "2 Chr 16:14*12759; Jer 34:5*22164; Amos 6:10*25145",
        "a": "q"
    },
    {
        "o": 8846,
        "r": "nkjv:1 Samuel:31:13",
        "w": 12,
        "l": {},
        "c": "2 Sam 2:4, 5*8882; 21:12–14*9487",
        "a": "r"
    }
]
