[
    {
        "o": 32915,
        "r": "esv:Philippians:3:1",
        "w": 2,
        "l": {},
        "t": "Or brothers*i and*i sisters*i ; also verses 13, 17",
        "a": "a"
    },
    {
        "o": 32915,
        "r": "esv:Philippians:3:1",
        "w": 2,
        "l": {},
        "c": "Philippians 4:4*32942; 1 Thessalonians 5:16*33163",
        "a": "b"
    },
    {
        "o": 32915,
        "r": "esv:Philippians:3:1",
        "w": 6,
        "l": {},
        "c": "2 Peter 1:12*34144",
        "a": "c"
    },
    {
        "o": 32916,
        "r": "esv:Philippians:3:2",
        "w": 2,
        "l": {},
        "c": "Psalm 22:16*15676; Psalm 22:20*15680; Isaiah 56:10–11*20879; Revelation 22:15*34850; Galatians 5:15*32634",
        "a": "d"
    },
    {
        "o": 32916,
        "r": "esv:Philippians:3:2",
        "w": 7,
        "l": {},
        "c": "2 Corinthians 11:13*32433",
        "a": "e"
    },
    {
        "o": 32917,
        "r": "esv:Philippians:3:3",
        "w": 0,
        "l": {},
        "c": "Romans 2:29*31296",
        "a": "f"
    },
    {
        "o": 32917,
        "r": "esv:Philippians:3:3",
        "w": 4,
        "l": {},
        "c": "John 4:23*29280",
        "a": "g"
    },
    {
        "o": 32917,
        "r": "esv:Philippians:3:3",
        "w": 6,
        "l": {},
        "c": "Galatians 5:25*32644; Jude 20*34382",
        "a": "h"
    },
    {
        "o": 32917,
        "r": "esv:Philippians:3:3",
        "w": 11,
        "l": {},
        "t": "Some manuscripts God*i in*i spirit*i",
        "a": "i"
    },
    {
        "o": 32917,
        "r": "esv:Philippians:3:3",
        "w": 12,
        "l": {},
        "c": "Romans 15:17*31669; Galatians 6:14*32662",
        "a": "j"
    },
    {
        "o": 32918,
        "r": "esv:Philippians:3:4",
        "w": 0,
        "l": {},
        "c": "2 Corinthians 11:18*32439",
        "a": "k"
    },
    {
        "o": 32919,
        "r": "esv:Philippians:3:5",
        "w": 0,
        "l": {},
        "c": "Genesis 17:12*450",
        "a": "l"
    },
    {
        "o": 32919,
        "r": "esv:Philippians:3:5",
        "w": 4,
        "l": {},
        "c": "2 Corinthians 11:22*32443",
        "a": "m"
    },
    {
        "o": 32919,
        "r": "esv:Philippians:3:5",
        "w": 9,
        "l": {},
        "c": "Romans 11:1*31543",
        "a": "n"
    },
    {
        "o": 32919,
        "r": "esv:Philippians:3:5",
        "w": 14,
        "l": {},
        "c": "2 Corinthians 11:22*32443",
        "a": "o"
    },
    {
        "o": 32919,
        "r": "esv:Philippians:3:5",
        "w": 22,
        "l": {},
        "c": "Acts 23:6*31020; Acts 26:5*31117",
        "a": "p"
    },
    {
        "o": 32920,
        "r": "esv:Philippians:3:6",
        "w": 0,
        "l": {},
        "c": "Acts 22:3–4*30984; Galatians 1:13–14*32512",
        "a": "q"
    },
    {
        "o": 32920,
        "r": "esv:Philippians:3:6",
        "w": 2,
        "l": {},
        "c": "Acts 8:3*30394",
        "a": "r"
    },
    {
        "o": 32920,
        "r": "esv:Philippians:3:6",
        "w": 7,
        "l": {},
        "c": "Philippians 3:9*32923",
        "a": "s"
    },
    {
        "o": 32920,
        "r": "esv:Philippians:3:6",
        "w": 13,
        "l": {},
        "t": "Greek in*i the*i law*i",
        "a": "t"
    },
    {
        "o": 32921,
        "r": "esv:Philippians:3:7",
        "w": 0,
        "l": {},
        "c": "Luke 14:33*28605",
        "a": "u"
    },
    {
        "o": 32921,
        "r": "esv:Philippians:3:7",
        "w": 4,
        "l": {},
        "c": "Hebrews 11:26*33807",
        "a": "v"
    },
    {
        "o": 32922,
        "r": "esv:Philippians:3:8",
        "w": 7,
        "l": {},
        "c": "2 Corinthians 5:15*32309",
        "a": "w"
    },
    {
        "o": 32922,
        "r": "esv:Philippians:3:8",
        "w": 11,
        "l": {},
        "c": "Isaiah 53:11*20831; Jeremiah 9:23–24*21361; John 17:3*29924; 2 Peter 1:3*34135",
        "a": "x"
    },
    {
        "o": 32922,
        "r": "esv:Philippians:3:8",
        "w": 20,
        "l": {},
        "c": "Luke 9:25*28299",
        "a": "y"
    },
    {
        "o": 32923,
        "r": "esv:Philippians:3:9",
        "w": 6,
        "l": {},
        "c": "Romans 10:5*31524; Philippians 3:6*32920",
        "a": "z"
    },
    {
        "o": 32923,
        "r": "esv:Philippians:3:9",
        "w": 17,
        "l": {},
        "c": "Romans 9:30*31514; 1 Corinthians 1:30*31751",
        "a": "a"
    },
    {
        "o": 32924,
        "r": "esv:Philippians:3:10",
        "w": 0,
        "l": {},
        "c": "Ephesians 4:13*32757",
        "a": "b"
    },
    {
        "o": 32924,
        "r": "esv:Philippians:3:10",
        "w": 5,
        "l": {},
        "c": "Romans 1:4*31233; Romans 6:5*31390",
        "a": "c"
    },
    {
        "o": 32924,
        "r": "esv:Philippians:3:10",
        "w": 11,
        "l": {},
        "c": "1 Peter 4:13*34106; 2 Corinthians 1:5*32210",
        "a": "d"
    },
    {
        "o": 32925,
        "r": "esv:Philippians:3:11",
        "w": 6,
        "l": {},
        "c": "Acts 26:7*31119",
        "a": "e"
    },
    {
        "o": 32927,
        "r": "esv:Philippians:3:12",
        "w": 4,
        "l": {},
        "c": "1 Timothy 6:12*33356; 1 Timothy 6:19*33363",
        "a": "f"
    },
    {
        "o": 32927,
        "r": "esv:Philippians:3:12",
        "w": 7,
        "l": {},
        "c": "Hebrews 11:40*33821; Hebrews 12:23*33848; Hebrews 5:9*33632",
        "a": "g"
    },
    {
        "o": 32928,
        "r": "esv:Philippians:3:13",
        "w": 16,
        "l": {},
        "c": "Psalm 45:10*16131; Luke 9:62*28344; Hebrews 6:1*33640",
        "a": "h"
    },
    {
        "o": 32929,
        "r": "esv:Philippians:3:14",
        "w": 6,
        "l": {},
        "c": "1 Corinthians 9:24*31942",
        "a": "i"
    },
    {
        "o": 32929,
        "r": "esv:Philippians:3:14",
        "w": 11,
        "l": {},
        "c": "Hebrews 3:1*33585; 1 Peter 5:10*34124; Romans 8:28*31469",
        "a": "j"
    },
    {
        "o": 32930,
        "r": "esv:Philippians:3:15",
        "w": 5,
        "l": {},
        "c": "1 Corinthians 2:6*31761; Matthew 5:48*25940",
        "a": "k"
    },
    {
        "o": 32930,
        "r": "esv:Philippians:3:15",
        "w": 13,
        "l": {},
        "c": "Galatians 5:10*32628",
        "a": "l"
    },
    {
        "o": 32930,
        "r": "esv:Philippians:3:15",
        "w": 16,
        "l": {},
        "c": "John 7:17*29458",
        "a": "m"
    },
    {
        "o": 32931,
        "r": "esv:Philippians:3:16",
        "w": 0,
        "l": {},
        "c": "Galatians 6:16*32664",
        "a": "n"
    },
    {
        "o": 32932,
        "r": "esv:Philippians:3:17",
        "w": 0,
        "l": {},
        "c": "Philippians 4:9*32948; 1 Corinthians 4:16*31814",
        "a": "o"
    },
    {
        "o": 32932,
        "r": "esv:Philippians:3:17",
        "w": 12,
        "l": {},
        "c": "1 Peter 5:3*34117",
        "a": "p"
    },
    {
        "o": 32933,
        "r": "esv:Philippians:3:18",
        "w": 0,
        "l": {},
        "c": "2 Corinthians 11:13*32433",
        "a": "q"
    },
    {
        "o": 32933,
        "r": "esv:Philippians:3:18",
        "w": 12,
        "l": {},
        "c": "Acts 20:31*30928",
        "a": "r"
    },
    {
        "o": 32934,
        "r": "esv:Philippians:3:19",
        "w": 0,
        "l": {},
        "c": "2 Corinthians 11:15*32436; 2 Thessalonians 1:9*33188; 2 Peter 2:1*34157; 2 Peter 2:3*34159",
        "a": "s"
    },
    {
        "o": 32934,
        "r": "esv:Philippians:3:19",
        "w": 3,
        "l": {},
        "c": "Romans 16:18*31707",
        "a": "t"
    },
    {
        "o": 32934,
        "r": "esv:Philippians:3:19",
        "w": 9,
        "l": {},
        "c": "Hosea 4:7*24604; 2 Corinthians 11:12*32432; Galatians 6:13*32661; Jude 13*34374",
        "a": "u"
    },
    {
        "o": 32934,
        "r": "esv:Philippians:3:19",
        "w": 15,
        "l": {},
        "c": "Romans 8:5*31444; Colossians 3:2*33027",
        "a": "v"
    },
    {
        "o": 32935,
        "r": "esv:Philippians:3:20",
        "w": 0,
        "l": {},
        "c": "Ephesians 2:19*32715",
        "a": "w"
    },
    {
        "o": 32935,
        "r": "esv:Philippians:3:20",
        "w": 6,
        "l": {},
        "c": "Acts 1:11*30125",
        "a": "x"
    },
    {
        "o": 32935,
        "r": "esv:Philippians:3:20",
        "w": 9,
        "l": {},
        "c": "1 Corinthians 1:7*31726",
        "a": "y"
    },
    {
        "o": 32936,
        "r": "esv:Philippians:3:21",
        "w": 2,
        "l": {},
        "c": "1 Corinthians 15:43–53*32157",
        "a": "z"
    },
    {
        "o": 32936,
        "r": "esv:Philippians:3:21",
        "w": 5,
        "l": {},
        "c": "Philippians 3:10*32924; Colossians 3:4*33029; Romans 8:29*31470",
        "a": "a"
    },
    {
        "o": 32936,
        "r": "esv:Philippians:3:21",
        "w": 11,
        "l": {},
        "c": "Ephesians 1:19*32689",
        "a": "b"
    },
    {
        "o": 32936,
        "r": "esv:Philippians:3:21",
        "w": 18,
        "l": {},
        "c": "1 Corinthians 15:28*32141",
        "a": "c"
    }
]
