[
    {
        "o": 34063,
        "r": "nkjv:Hebrews:8:1",
        "w": 17,
        "l": {},
        "c": "Ps 68:18*16598; 110:1*17584; Eph 1:20*33014; Col 3:1*33362; Heb 2:17*33942; 3:1*33946; 10:12*34126",
        "a": "a"
    },
    {
        "o": 34064,
        "r": "nkjv:Hebrews:8:2",
        "w": 2,
        "l": {},
        "c": "Heb 9:8, 12*34087",
        "a": "b"
    },
    {
        "o": 34064,
        "r": "nkjv:Hebrews:8:2",
        "w": 6,
        "l": {},
        "c": "Heb 9:11, 24*34091",
        "a": "c"
    },
    {
        "o": 34065,
        "r": "nkjv:Hebrews:8:3",
        "w": 0,
        "l": {},
        "c": "Rom 4:25*31639; 5:6, 8*31648; Gal 2:20*32867; Eph 5:2*33110; Heb 5:1*33989; 8:4*34066",
        "a": "d"
    },
    {
        "o": 34065,
        "r": "nkjv:Hebrews:8:3",
        "w": 12,
        "l": {},
        "c": "Eph 5:2*33110; Heb 9:14*34094",
        "a": "e"
    },
    {
        "o": 34067,
        "r": "nkjv:Hebrews:8:5",
        "w": 1,
        "l": {},
        "c": "Heb 9:23, 24*34105",
        "a": "f"
    },
    {
        "o": 34067,
        "r": "nkjv:Hebrews:8:5",
        "w": 4,
        "l": {},
        "c": "Col 2:17*33353; Heb 10:1*34113",
        "a": "g"
    },
    {
        "o": 34067,
        "r": "nkjv:Hebrews:8:5",
        "w": 25,
        "l": {},
        "c": "Ex 25:40*2461",
        "a": "h"
    },
    {
        "o": 34068,
        "r": "nkjv:Hebrews:8:6",
        "w": 1,
        "l": {},
        "c": "2 Cor 3:6–8*32566",
        "a": "i"
    },
    {
        "o": 34068,
        "r": "nkjv:Hebrews:8:6",
        "w": 16,
        "l": {},
        "c": "Luke 22:20*29172; Heb 7:22*34054",
        "a": "j"
    },
    {
        "o": 34070,
        "r": "nkjv:Hebrews:8:7",
        "w": 2,
        "l": {},
        "c": "Ex 3:8*1739; 19:5*2233",
        "a": "k"
    },
    {
        "o": 34071,
        "r": "nkjv:Hebrews:8:8",
        "w": 6,
        "l": {},
        "c": "Jer 31:31–34*22071",
        "a": "l"
    },
    {
        "o": 34073,
        "r": "nkjv:Hebrews:8:10",
        "w": 18,
        "l": {},
        "c": "Jer 31:33*22073; Rom 11:27*31855; Heb 10:16*34130",
        "a": "m"
    },
    {
        "o": 34073,
        "r": "nkjv:Hebrews:8:10",
        "w": 34,
        "l": {},
        "c": "Zech 8:8*25774",
        "a": "n"
    },
    {
        "o": 34074,
        "r": "nkjv:Hebrews:8:11",
        "w": 0,
        "l": {},
        "c": "Is 54:13*20964; John 6:45*29643; 1 John 2:27*34649",
        "a": "o"
    },
    {
        "o": 34074,
        "r": "nkjv:Hebrews:8:11",
        "w": 13,
        "l": {},
        "c": "Jer 31:34*22074",
        "a": "p"
    },
    {
        "o": 34075,
        "r": "nkjv:Hebrews:8:12",
        "w": 7,
        "l": {},
        "c": "Rom 11:27*31855",
        "a": "q"
    },
    {
        "o": 34076,
        "r": "nkjv:Hebrews:8:13",
        "w": 0,
        "l": {},
        "c": "2 Cor 5:17*32621; Heb 1:11*33918",
        "a": "r"
    }
]
