[
    {
        "o": 24199,
        "r": "nkjv:Ezekiel:45:1",
        "w": 2,
        "l": {},
        "c": "Num 26:52–56*4993; Ezek 47:22*24279",
        "a": "a"
    },
    {
        "o": 24199,
        "r": "nkjv:Ezekiel:45:1",
        "w": 11,
        "l": {},
        "c": "Ezek 48:8, 9*24290",
        "a": "b"
    },
    {
        "o": 24200,
        "r": "nkjv:Ezekiel:45:2",
        "w": 10,
        "l": {},
        "c": "Ezek 42:20*24130",
        "a": "c"
    },
    {
        "o": 24201,
        "r": "nkjv:Ezekiel:45:3",
        "w": 15,
        "l": {},
        "c": "Ezek 48:10*24292",
        "a": "d"
    },
    {
        "o": 24202,
        "r": "nkjv:Ezekiel:45:4",
        "w": 2,
        "l": {},
        "c": "Ezek 48:10, 11*24292",
        "a": "e"
    },
    {
        "o": 24203,
        "r": "nkjv:Ezekiel:45:5",
        "w": 0,
        "l": {},
        "c": "Ezek 48:13*24295",
        "a": "f"
    },
    {
        "o": 24203,
        "r": "nkjv:Ezekiel:45:5",
        "w": 22,
        "l": {},
        "c": "Ezek 40:17*24038",
        "a": "g"
    },
    {
        "o": 24205,
        "r": "nkjv:Ezekiel:45:6",
        "w": 0,
        "l": {},
        "c": "Ezek 48:15*24297",
        "a": "h"
    },
    {
        "o": 24206,
        "r": "nkjv:Ezekiel:45:7",
        "w": 0,
        "l": {},
        "c": "Ezek 48:21*24303",
        "a": "i"
    },
    {
        "o": 24207,
        "r": "nkjv:Ezekiel:45:8",
        "w": 8,
        "l": {},
        "c": "Is 11:3–5*19991; Jer 22:17*21796; Ezek 22:27*23484",
        "a": "j"
    },
    {
        "o": 24209,
        "r": "nkjv:Ezekiel:45:9",
        "w": 4,
        "l": {},
        "c": "Ezek 44:6*24170",
        "a": "k"
    },
    {
        "o": 24209,
        "r": "nkjv:Ezekiel:45:9",
        "w": 9,
        "l": {},
        "c": "Jer 22:3*21781; Zech 8:16*25782",
        "a": "l"
    },
    {
        "o": 24210,
        "r": "nkjv:Ezekiel:45:10",
        "w": 2,
        "l": {},
        "c": "Lev 19:36*3653; Deut 25:15*6130; Prov 16:11*18805; Amos 8:4–6*25177; Mic 6:10, 11*25387",
        "a": "m"
    },
    {
        "o": 24212,
        "r": "nkjv:Ezekiel:45:12",
        "w": 0,
        "l": {},
        "c": "Ex 30:13*2638; Lev 27:25*3961; Num 3:47*4114",
        "a": "n"
    },
    {
        "o": 24215,
        "r": "nkjv:Ezekiel:45:15",
        "w": 28,
        "l": {},
        "c": "Lev 1:4*3039; 6:30*3182",
        "a": "o"
    },
    {
        "o": 24217,
        "r": "nkjv:Ezekiel:45:17",
        "w": 4,
        "l": {},
        "c": "Ezek 46:4–12*24232",
        "a": "p"
    },
    {
        "o": 24219,
        "r": "nkjv:Ezekiel:45:18",
        "w": 24,
        "l": {},
        "c": "Lev 16:16, 33*3547; Ezek 43:22, 26*24156",
        "a": "q"
    },
    {
        "o": 24220,
        "r": "nkjv:Ezekiel:45:19",
        "w": 0,
        "l": {},
        "c": "Lev 16:18–20*3549; Ezek 43:20*24154",
        "a": "r"
    },
    {
        "o": 24221,
        "r": "nkjv:Ezekiel:45:20",
        "w": 11,
        "l": {},
        "c": "Lev 4:27*3118; Ps 19:12*15714",
        "a": "s"
    },
    {
        "o": 24222,
        "r": "nkjv:Ezekiel:45:21",
        "w": 0,
        "l": {},
        "c": "Ex 12:18*2013; Lev 23:5, 6*3753; Num 9:2, 3*4361; 28:16, 17*5053; Deut 16:1*5878",
        "a": "t"
    },
    {
        "o": 24223,
        "r": "nkjv:Ezekiel:45:22",
        "w": 17,
        "l": {},
        "c": "Lev 4:14*3105",
        "a": "u"
    },
    {
        "o": 24224,
        "r": "nkjv:Ezekiel:45:23",
        "w": 1,
        "l": {},
        "c": "Lev 23:8*3757",
        "a": "v"
    },
    {
        "o": 24224,
        "r": "nkjv:Ezekiel:45:23",
        "w": 26,
        "l": {},
        "c": "Num 28:15, 22, 30*5052; 29:5, 11, 16, 19*5076",
        "a": "w"
    },
    {
        "o": 24225,
        "r": "nkjv:Ezekiel:45:24",
        "w": 0,
        "l": {},
        "c": "Num 28:12–15*5048; Ezek 46:5, 7*24233",
        "a": "x"
    },
    {
        "o": 24226,
        "r": "nkjv:Ezekiel:45:25",
        "w": 12,
        "l": {},
        "c": "Lev 23:34*3787; Num 29:12*5085; Deut 16:13*5892; 2 Chr 5:3*12476; 7:8, 10*12542",
        "a": "y"
    }
]
