[
    {
        "o": 18073,
        "r": "csb:Psalm:132:1",
        "w": 8,
        "l": {},
        "c": "2Sm 16:12*9327",
        "a": "a"
    },
    {
        "o": 18074,
        "r": "csb:Psalm:132:2",
        "w": 17,
        "l": {},
        "c": "Gn 49:24*1646; Is 49:26*20904; 60:16*21102",
        "a": "b"
    },
    {
        "o": 18076,
        "r": "csb:Psalm:132:4",
        "w": 12,
        "l": {},
        "c": "Pr 6:4*18530",
        "a": "c"
    },
    {
        "o": 18077,
        "r": "csb:Psalm:132:5",
        "w": 15,
        "l": {},
        "c": "1Ch 22:7*12161; Ac 7:46*30732",
        "a": "d"
    },
    {
        "o": 18078,
        "r": "csb:Psalm:132:6",
        "w": 6,
        "l": {},
        "t": "132:6*r = Bethlehem",
        "a": "e"
    },
    {
        "o": 18078,
        "r": "csb:Psalm:132:6",
        "w": 6,
        "l": {},
        "c": "Gn 35:19*1134; Ru 4:11*7970; 1Sm 17:12*8444; Mc 5:2*25500",
        "a": "f"
    },
    {
        "o": 18078,
        "r": "csb:Psalm:132:6",
        "w": 14,
        "l": {},
        "t": "132:6*r = Kiriath-jearim",
        "a": "g"
    },
    {
        "o": 18078,
        "r": "csb:Psalm:132:6",
        "w": 14,
        "l": {},
        "c": "1Sm 7:1*8141",
        "a": "h"
    },
    {
        "o": 18079,
        "r": "csb:Psalm:132:7",
        "w": 10,
        "l": {},
        "c": "1Ch 28:2*12349; Ps 99:5*17315",
        "a": "i"
    },
    {
        "o": 18080,
        "r": "csb:Psalm:132:8",
        "w": 12,
        "l": {},
        "c": "2Ch 6:41*12555; Ps 68:1*16623; 78:61*16927",
        "a": "j"
    },
    {
        "o": 18081,
        "r": "csb:Psalm:132:9",
        "w": 14,
        "l": {},
        "c": "Jb 29:14*15050; Ps 149:5*18355",
        "a": "k"
    },
    {
        "o": 18082,
        "r": "csb:Psalm:132:10",
        "w": 12,
        "l": {},
        "t": "132:10*r = the king",
        "a": "l"
    },
    {
        "o": 18082,
        "r": "csb:Psalm:132:10",
        "w": 12,
        "l": {},
        "c": "2Ch 6:42*12556",
        "a": "m"
    },
    {
        "o": 18083,
        "r": "csb:Psalm:132:11",
        "w": 19,
        "l": {},
        "t": "132:11*r Lit set the fruit of your belly",
        "a": "n"
    },
    {
        "o": 18083,
        "r": "csb:Psalm:132:11",
        "w": 22,
        "l": {},
        "c": "2Sm 7:12–16*9055; Ps 89:3*17115; Ac 2:30*30522",
        "a": "o"
    },
    {
        "o": 18084,
        "r": "csb:Psalm:132:12",
        "w": 22,
        "l": {},
        "c": "1Kg 8:25*9958; Lk 1:32*28168",
        "a": "p"
    },
    {
        "o": 18085,
        "r": "csb:Psalm:132:13",
        "w": 12,
        "l": {},
        "c": "Ps 68:16*16638; 78:68*16934",
        "a": "q"
    },
    {
        "o": 18086,
        "r": "csb:Psalm:132:14",
        "w": 16,
        "l": {},
        "c": "Mt 23:21*27033",
        "a": "r"
    },
    {
        "o": 18087,
        "r": "csb:Psalm:132:15",
        "w": 12,
        "l": {},
        "c": "Ps 107:9*17541; 147:14*18326",
        "a": "s"
    },
    {
        "o": 18088,
        "r": "csb:Psalm:132:16",
        "w": 14,
        "l": {},
        "c": "2Ch 6:41*12555",
        "a": "t"
    },
    {
        "o": 18089,
        "r": "csb:Psalm:132:17",
        "w": 8,
        "l": {},
        "c": "2Sm 23:5*9565; Lk 1:69*28209",
        "a": "u"
    },
    {
        "o": 18089,
        "r": "csb:Psalm:132:17",
        "w": 13,
        "l": {},
        "t": "132:17*r Or dominion",
        "a": "v"
    },
    {
        "o": 18089,
        "r": "csb:Psalm:132:17",
        "w": 17,
        "l": {},
        "c": "1Kg 11:36*10104",
        "a": "w"
    },
    {
        "o": 18090,
        "r": "csb:Psalm:132:18",
        "w": 6,
        "l": {},
        "c": "Jb 8:22*14517",
        "a": "x"
    },
    {
        "o": 18090,
        "r": "csb:Psalm:132:18",
        "w": 11,
        "l": {},
        "t": "132:18*r Lit but on him his crown",
        "a": "y"
    },
    {
        "o": 18090,
        "r": "csb:Psalm:132:18",
        "w": 14,
        "l": {},
        "c": "Ps 21:3*15776",
        "a": "z"
    }
]
